README.md
setup.py
yxutils/__init__.py
yxutils/__main__.py
yxutils/osearch.py
yxutils/xminheap.py
yxutils.egg-info/PKG-INFO
yxutils.egg-info/SOURCES.txt
yxutils.egg-info/dependency_links.txt
yxutils.egg-info/entry_points.txt
yxutils.egg-info/top_level.txt